deicode/__init__.py
deicode/_rpca_defaults.py
deicode/base.py
deicode/citations.bib
deicode/matrix_completion.py
deicode/optspace.py
deicode/preprocessing.py
deicode/rpca.py
deicode/testing.py
deicode/q2/__init__.py
deicode/q2/plugin_setup.py
deicode/scripts/__init__.py
deicode/scripts/_standalone_rpca.py
deicode-0.2.4.dist-info/COPYING.txt
deicode-0.2.4.dist-info/METADATA
deicode-0.2.4.dist-info/WHEEL
deicode-0.2.4.dist-info/entry_points.txt
deicode-0.2.4.dist-info/top_level.txt
deicode-0.2.4.dist-info/RECORD
