Metadata-Version: 2.1
Name: deicode
Version: 0.2.4
Summary: Robust Aitchison compositional biplots from sparse count data
Home-page: UNKNOWN
Author: deicode development team
Author-email: cameronmartino@gmail.com
Maintainer: deicode development team
Maintainer-email: cameronmartino@gmail.com
License: BSD-3-Clause
Platform: UNKNOWN
Classifier: Development Status :: 3 - Alpha
Classifier: License :: OSI Approved :: BSD License
Classifier: Topic :: Software Development :: Libraries
Classifier: Topic :: Scientific/Engineering
Classifier: Topic :: Scientific/Engineering :: Bio-Informatics
Classifier: Programming Language :: Python :: 3
Classifier: Programming Language :: Python :: 3 :: Only
Classifier: Operating System :: Unix
Classifier: Operating System :: POSIX
Classifier: Operating System :: MacOS :: MacOS X
Requires-Dist: numpy (>=1.12.1)
Requires-Dist: click
Requires-Dist: pandas (>=0.10.0)
Requires-Dist: scipy (>=0.19.1)
Requires-Dist: nose (>=1.3.7)
Requires-Dist: scikit-bio (>0.5.3)
Requires-Dist: biom-format
Requires-Dist: h5py
